strands_mlx/__init__.py
strands_mlx/cli.py
strands_mlx/mlx_model.py
strands_mlx/mlx_session_manager.py
strands_mlx/mlx_vision_model.py
strands_mlx/tools/__init__.py
strands_mlx/tools/dataset_splitter.py
strands_mlx/tools/mlx_invoke.py
strands_mlx/tools/mlx_trainer.py
strands_mlx/tools/mlx_vision_invoke.py
strands_mlx/tools/mlx_vision_trainer.py
strands_mlx/tools/validate_training_data.py
strands_mlx-0.2.6.dist-info/licenses/LICENSE
strands_mlx-0.2.6.dist-info/METADATA
strands_mlx-0.2.6.dist-info/WHEEL
strands_mlx-0.2.6.dist-info/entry_points.txt
strands_mlx-0.2.6.dist-info/top_level.txt
strands_mlx-0.2.6.dist-info/RECORD
