Metadata-Version: 2.4
Name: strands-mlx
Version: 0.2.6
Summary: Use MLX in Strands Agents
Author-email: Cagatay Cali <cagataycali@icloud.com>
License: MIT
Project-URL: Homepage, https://github.com/cagataycali/strands-mlx
Project-URL: Repository, https://github.com/cagataycali/strands-mlx
Project-URL: Issues, https://github.com/cagataycali/strands-mlx/issues
Keywords: strands,agents,fine-tuning,lora,llm,mlx-lm
Classifier: Development Status :: 3 - Alpha
Classifier: Intended Audience :: Developers
Classifier: License :: OSI Approved :: MIT License
Classifier: Programming Language :: Python :: 3
Classifier: Programming Language :: Python :: 3.10
Classifier: Programming Language :: Python :: 3.11
Classifier: Programming Language :: Python :: 3.12
Classifier: Programming Language :: Python :: 3.13
Classifier: Topic :: Scientific/Engineering :: Artificial Intelligence
Classifier: Topic :: Software Development :: Libraries :: Python Modules
Requires-Python: <3.14,>=3.10
License-File: LICENSE
Requires-Dist: strands-agents
Requires-Dist: huggingface_hub
Requires-Dist: mlx-lm
Requires-Dist: mlx-vlm
Provides-Extra: dev
Requires-Dist: pytest>=7.0; extra == "dev"
Requires-Dist: pytest-asyncio; extra == "dev"
Requires-Dist: black; extra == "dev"
Requires-Dist: isort; extra == "dev"
Requires-Dist: mypy; extra == "dev"
Requires-Dist: ruff; extra == "dev"
Provides-Extra: vision
Requires-Dist: mlx-vlm>=0.3.0; extra == "vision"
Requires-Dist: pillow>=10.0.0; extra == "vision"
Requires-Dist: torch>=2.0.0; extra == "vision"
Requires-Dist: torchvision>=0.15.0; extra == "vision"
Requires-Dist: soundfile>=0.13.0; extra == "vision"
Provides-Extra: all
Requires-Dist: strands-agents-tools; extra == "all"
Requires-Dist: pytest>=7.0; extra == "all"
Requires-Dist: pytest-asyncio; extra == "all"
Requires-Dist: black; extra == "all"
Requires-Dist: isort; extra == "all"
Requires-Dist: mypy; extra == "all"
Requires-Dist: ruff; extra == "all"
Requires-Dist: mlx-vlm>=0.3.0; extra == "all"
Requires-Dist: pillow>=10.0.0; extra == "all"
Requires-Dist: torch>=2.0.0; extra == "all"
Requires-Dist: torchvision>=0.15.0; extra == "all"
Requires-Dist: soundfile>=0.13.0; extra == "all"
Dynamic: license-file
